{
  "@context": [
    "http://iiif.io/api/presentation/2/context.json",
    "http://files.universalviewer.io/ld/ixif/0/context.json"
  ],
  "@id": "http://files.universalviewer.io/manifests/adiks/Add_11831.json",
  "@type": "sc:Manifest",
  "label": "Add_4709",
  "description": "Pentateuch with the Five Scrolls, Psalms, Job and the Haftarot. Italy, 1486. Modelled for the British Library’s Hebrew Manuscript Digitisation Project, funded by The Polonsky Foundation. Special thanks to Kristin Phelps.",
  "metadata": [
    {
      "label": "Credits",
      "value": "Modelling: <a href='https://twitter.com/BL_AdiKS'>Adi Keinan-Schoonbaert</a>"
    },
    {
      "label": "Date",
      "value": "30/04/2016"
    }
  ],
  "mediaSequences": [
    {
      "@id": "http://universalviewer.io/xsequence/s0",
      "@type": "ixif:MediaSequence",
      "label": "XSequence 0",
      "elements": [
        {
          "@id": "http://files.universalviewer.io/manifests/adiks/Add_4709/Add_4709.json",
          "@type": "dctypes:PhysicalObject",
          "format": "application/vnd.threejs+json",
          "label": "Add_4709",
          "thumbnail": "http://files.universalviewer.io/manifests/adiks/Add_4709/thumb.jpg"
        }
      ]
    }
  ]
}